mythos/__init__.py
mythos/mythos/__init__.py
mythos/mythos/__version__.py
mythos-2021.1.15.0.dist-info/LICENSE
mythos-2021.1.15.0.dist-info/METADATA
mythos-2021.1.15.0.dist-info/WHEEL
mythos-2021.1.15.0.dist-info/top_level.txt
mythos-2021.1.15.0.dist-info/RECORD
